Metadata-Version: 2.4
Name: tapm-instrumentation-llamaindex
Version: 0.43.2
Summary: OpenTelemetry LlamaIndex instrumentation
License: Apache-2.0
Author: Wilson Cai
Author-email: wilsonxscai@tencent.com
Requires-Python: >=3.9,<4
Classifier: License :: OSI Approved :: Apache Software License
Classifier: Programming Language :: Python :: 3
Classifier: Programming Language :: Python :: 3.9
Classifier: Programming Language :: Python :: 3.10
Classifier: Programming Language :: Python :: 3.11
Classifier: Programming Language :: Python :: 3.12
Classifier: Programming Language :: Python :: 3.13
Classifier: Programming Language :: Python :: 3.14
Provides-Extra: instruments
Provides-Extra: llamaparse
Requires-Dist: inflection (>=0.5.1,<0.6.0)
Requires-Dist: llama-index-llms-openai-like (==0.4.0)
Requires-Dist: opentelemetry-api (>=1.28.0,<2.0.0)
Requires-Dist: opentelemetry-instrumentation (>=0.50b0)
Requires-Dist: opentelemetry-semantic-conventions (>=0.50b0)
Requires-Dist: tapm-semantic-conventions-ai (==0.4.12)
Project-URL: Repository, https://github.com/traceloop/openllmetry/tree/main/packages/opentelemetry-instrumentation-llamaindex
